django_es_utils/__init__.py
django_es_utils/analyzers.py
django_es_utils/connection.py
django_es_utils/document.py
django_es_utils/helpers.py
django_es_utils/mock.py
django_es_utils-1.0.3.dist-info/LICENSE
django_es_utils-1.0.3.dist-info/METADATA
django_es_utils-1.0.3.dist-info/WHEEL
django_es_utils-1.0.3.dist-info/top_level.txt
django_es_utils-1.0.3.dist-info/RECORD
