Metadata-Version: 2.1
Name: django-es-utils
Version: 1.0.3
Summary: Elasticsearch utilities for Django projects.
Home-page: https://github.com/Edraak/django-es-utils
Author: Fahmi Al-Najjar
Author-email: fahmi.najjar@gmail.com
License: UNKNOWN
Platform: UNKNOWN
Classifier: Programming Language :: Python :: 3
Classifier: License :: OSI Approved :: MIT License
Classifier: Operating System :: OS Independent
Requires-Dist: Django (==1.8)
Requires-Dist: requests
Requires-Dist: urllib3 (<1.22,>=1.21.1)
Requires-Dist: elasticsearch (==6.3.0)
Requires-Dist: elasticsearch-dsl (==6.2.1)
Requires-Dist: ElasticMock (==1.3.2)
